ipydeps/__init__.py
ipydeps/__main__.py
ipydeps/config.py
ipydeps/data/libs2.txt
ipydeps/data/libs3.txt
ipydeps/ipydeps.py
ipydeps/logger.py
ipydeps/utils.py
ipydeps-2025.15.1079.dist-info/LICENSE
ipydeps-2025.15.1079.dist-info/METADATA
ipydeps-2025.15.1079.dist-info/WHEEL
ipydeps-2025.15.1079.dist-info/RECORD
