Metadata-Version: 2.3
Name: ipydeps
Version: 2025.15.1079
Summary: A pip interface wrapper for installing packages from within Jupyter notebooks.
License: MIT
Author: Bill Allen
Author-email: billallen256@gmail.com
Requires-Python: >=3.6,<4.0
Classifier: License :: OSI Approved :: MIT License
Classifier: Programming Language :: Python :: 3
Classifier: Programming Language :: Python :: 3.6
Classifier: Programming Language :: Python :: 3.7
Classifier: Programming Language :: Python :: 3.8
Classifier: Programming Language :: Python :: 3.9
Classifier: Programming Language :: Python :: 3.10
Classifier: Programming Language :: Python :: 3.11
Classifier: Programming Language :: Python :: 3.12
Classifier: Programming Language :: Python :: 3.13
Requires-Dist: ipylogging (>=2020.342.1)
Requires-Dist: pip (>=20.0)
Requires-Dist: pypki3 (>=2023.111.38)
Requires-Dist: temppath (>=2021.236.907)
Project-URL: Homepage, http://github.com/nbgallery/ipydeps
